pincode_package/__init__.py
pincode_package/api.py
pincode_package/cache.py
pincode_package/cli.py
pincode_package/exceptions.py
pincode_package/utils.py
pincode_package-1.0.dist-info/licenses/LICENSE
pincode_package-1.0.dist-info/METADATA
pincode_package-1.0.dist-info/WHEEL
pincode_package-1.0.dist-info/entry_points.txt
pincode_package-1.0.dist-info/top_level.txt
pincode_package-1.0.dist-info/RECORD
