Metadata-Version: 2.4
Name: pincode_package
Version: 1.0
Summary: Fetch live Indian pincode details using PostalPincode.in API
Author-email: Sreelakshmi K S <kssreelakshmi2211@gmail.com>
License: MIT
Project-URL: Homepage, https://github.com/kssreelakshmi/pincode-package.git
Requires-Python: >=3.7
License-File: LICENSE
Requires-Dist: requests>=2.25
Requires-Dist: httpx
Provides-Extra: dev
Requires-Dist: pytest; extra == "dev"
Dynamic: license-file
